arr_sum/__init__.py
arr_sum/arr_sum.py
arr_sum/result.py
mult_table/__init__.py
mult_table/table.py
calc_processing-0.0.2.dist-info/METADATA
calc_processing-0.0.2.dist-info/WHEEL
calc_processing-0.0.2.dist-info/top_level.txt
calc_processing-0.0.2.dist-info/RECORD
