Metadata-Version: 2.1
Name: calc-processing
Version: 0.0.2
Summary: Mult Table and array sum
Home-page: https://github.com/TucanoWeb/projetos/tree/master/python/calc-package
Author: TucanoWeb
Author-email: suporte@tucanoweb.com.br
License: UNKNOWN
Platform: UNKNOWN
Requires-Python: >=3.8
